harser/__init__.py
harser-0.1.dist-info/DESCRIPTION.rst
harser-0.1.dist-info/METADATA
harser-0.1.dist-info/RECORD
harser-0.1.dist-info/WHEEL
harser-0.1.dist-info/metadata.json
harser-0.1.dist-info/top_level.txt
