Metadata-Version: 2.0
Name: harser
Version: 0.1
Summary: Easy way for HTML parsing and building XPath.
Home-page: https://github.com/sihaelov/harser
Author: Michael Sinov
Author-email: sihaelov@gmail.com
License: MIT License
Platform: UNKNOWN
Classifier: Intended Audience :: Developers
Classifier: License :: OSI Approved :: MIT License
Classifier: Programming Language :: Python
Classifier: Programming Language :: Python :: 2.6
Classifier: Programming Language :: Python :: 2.7
Classifier: Programming Language :: Python :: 3.3
Classifier: Programming Language :: Python :: 3.4
Classifier: Programming Language :: Python :: 3.5
Classifier: Topic :: Text Processing :: Markup :: HTML
Classifier: Topic :: Software Development :: Libraries :: Python Modules
Requires-Dist: lxml
Requires-Dist: six
